{"menu": [{"items": [{"id": 1, "name": "Mac and Cheese", "price": 3.99, "category": "Appetizers"}, {"id": 2, "name": "Coleslaw", "price": 1.5, "category": "Appetizers"}, {"id": 3, "name": "Corn on the Cob", "price": 1.99, "category": "Appetizers"}, {"id": 4, "name": "Potato Salad", "price": 2.5, "category": "Appetizers"}, {"id": 5, "name": "Baked Beans", "price": 1.5, "category": "Appetizers"}, {"id": 6, "name": "Burger", "price": 6.5, "category": "Entrees"}, {"id": 7, "name": "Smoked Brisket", "price": 7.99, "category": "Entrees"}, {"id": 8, "name": "Pulled Pork Sandwitch", "price": 6.99, "category": "Entrees"}, {"id": 9, "name": "Ribs", "price": 12.99, "category": "Entrees"}, {"id": 10, "name": "BBQ Chicken", "price": 6.99, "category": "Entrees"}, {"id": 11, "name": "Grilled Chicken", "price": 5.99, "category": "Entrees"}, {"id": 12, "name": "Hot Dog", "price": 2.99, "category": "Entrees"}, {"id": 13, "name": "Pork Chops", "price": 7.99, "category": "Entrees"}, {"id": 14, "name": "Apple Pie", "price": 4.99, "category": "Desserts"}, {"id": 15, "name": "Cherry Pie", "price": 4.99, "category": "Desserts"}, {"id": 16, "name": "Chocolate Chip Cookies", "price": 2.5, "category": "Desserts"}, {"id": 17, "name": "Brownies", "price": 2.99, "category": "Desserts"}, {"id": 18, "name": "Coca-Cola", "price": 1.99, "category": "Drinks"}, {"id": 19, "name": "Pepsi", "price": 1.85, "category": "Drinks"}, {"id": 20, "name": "Water", "price": 0.0, "category": "Drinks"}]}]}